{
  "timestamp": "2025-09-17T11:06:34.991166",
  "models": {
    "endorlabs_malicious_classifier": {
      "model_name": "endorlabs_malicious_classifier",
      "type": "huggingface",
      "use_peft": true,
      "base_model_id": "microsoft/codebert-base-mlm",
      "adapter_id": "endorlabs/malicious-package-classifier-bert-mal-only",
      "model_id": null,
      "inference_method": "model_service"
    }
  },
  "samples_count": 26,
  "results": [
    {
      "model_name": "endorlabs_malicious_classifier",
      "sample_id": "npm_0x-smart-contracts",
      "ground_truth": 1,
      "prediction": 1,
      "confidence": 0.993126392364502,
      "inference_time_seconds": 0.2978639602661133,
      "cost_usd": null,
      "success": true,
      "error_message": null,
      "explanation": "",
      "raw_output": ""
    },
    {
      "model_name": "endorlabs_malicious_classifier",
      "sample_id": "npm_got-fetch",
      "ground_truth": 1,
      "prediction": 1,
      "confidence": 0.9913831353187561,
      "inference_time_seconds": 0.2115769386291504,
      "cost_usd": null,
      "success": true,
      "error_message": null,
      "explanation": "",
      "raw_output": ""
    },
    {
      "model_name": "endorlabs_malicious_classifier",
      "sample_id": "npm_content-disposition",
      "ground_truth": 0,
      "prediction": 1,
      "confidence": 0.9894092082977295,
      "inference_time_seconds": 0.2126908302307129,
      "cost_usd": null,
      "success": true,
      "error_message": null,
      "explanation": "",
      "raw_output": ""
    },
    {
      "model_name": "endorlabs_malicious_classifier",
      "sample_id": "npm_parseurl",
      "ground_truth": 0,
      "prediction": 1,
      "confidence": 0.9911887645721436,
      "inference_time_seconds": 0.19526910781860352,
      "cost_usd": null,
      "success": true,
      "error_message": null,
      "explanation": "",
      "raw_output": ""
    },
    {
      "model_name": "endorlabs_malicious_classifier",
      "sample_id": "npm_000webhost-analytics",
      "ground_truth": 1,
      "prediction": 1,
      "confidence": 0.99116450548172,
      "inference_time_seconds": 0.2216169834136963,
      "cost_usd": null,
      "success": true,
      "error_message": null,
      "explanation": "",
      "raw_output": ""
    },
    {
      "model_name": "endorlabs_malicious_classifier",
      "sample_id": "pypi_requests",
      "ground_truth": 0,
      "prediction": 1,
      "confidence": 0.9935117363929749,
      "inference_time_seconds": 0.19990086555480957,
      "cost_usd": null,
      "success": true,
      "error_message": null,
      "explanation": "",
      "raw_output": ""
    },
    {
      "model_name": "endorlabs_malicious_classifier",
      "sample_id": "pypi_git-github-reflog",
      "ground_truth": 0,
      "prediction": 1,
      "confidence": 0.9915062785148621,
      "inference_time_seconds": 0.19262099266052246,
      "cost_usd": null,
      "success": true,
      "error_message": null,
      "explanation": "",
      "raw_output": ""
    },
    {
      "model_name": "endorlabs_malicious_classifier",
      "sample_id": "npm_formatter",
      "ground_truth": 0,
      "prediction": 1,
      "confidence": 0.9903358221054077,
      "inference_time_seconds": 0.23507094383239746,
      "cost_usd": null,
      "success": true,
      "error_message": null,
      "explanation": "",
      "raw_output": ""
    },
    {
      "model_name": "endorlabs_malicious_classifier",
      "sample_id": "npm_tool",
      "ground_truth": 0,
      "prediction": 1,
      "confidence": 0.9917391538619995,
      "inference_time_seconds": 0.21799612045288086,
      "cost_usd": null,
      "success": true,
      "error_message": null,
      "explanation": "",
      "raw_output": ""
    },
    {
      "model_name": "endorlabs_malicious_classifier",
      "sample_id": "npm_eslint-config-prettier",
      "ground_truth": 1,
      "prediction": 1,
      "confidence": 0.9942097663879395,
      "inference_time_seconds": 0.22043991088867188,
      "cost_usd": null,
      "success": true,
      "error_message": null,
      "explanation": "",
      "raw_output": ""
    },
    {
      "model_name": "endorlabs_malicious_classifier",
      "sample_id": "npm_000webhost-api",
      "ground_truth": 1,
      "prediction": 1,
      "confidence": 0.9910529255867004,
      "inference_time_seconds": 0.21728062629699707,
      "cost_usd": null,
      "success": true,
      "error_message": null,
      "explanation": "",
      "raw_output": ""
    },
    {
      "model_name": "endorlabs_malicious_classifier",
      "sample_id": "npm_openssl-wrapper",
      "ground_truth": 0,
      "prediction": 1,
      "confidence": 0.9928573369979858,
      "inference_time_seconds": 0.22104787826538086,
      "cost_usd": null,
      "success": true,
      "error_message": null,
      "explanation": "",
      "raw_output": ""
    },
    {
      "model_name": "endorlabs_malicious_classifier",
      "sample_id": "npm_vant",
      "ground_truth": 1,
      "prediction": 1,
      "confidence": 0.9934107661247253,
      "inference_time_seconds": 0.27443504333496094,
      "cost_usd": null,
      "success": true,
      "error_message": null,
      "explanation": "",
      "raw_output": ""
    },
    {
      "model_name": "endorlabs_malicious_classifier",
      "sample_id": "pypi_certifi",
      "ground_truth": 0,
      "prediction": 1,
      "confidence": 0.9928695559501648,
      "inference_time_seconds": 0.26168394088745117,
      "cost_usd": null,
      "success": true,
      "error_message": null,
      "explanation": "",
      "raw_output": ""
    },
    {
      "model_name": "endorlabs_malicious_classifier",
      "sample_id": "npm_cli-cursor",
      "ground_truth": 0,
      "prediction": 1,
      "confidence": 0.9930965304374695,
      "inference_time_seconds": 0.2356863021850586,
      "cost_usd": null,
      "success": true,
      "error_message": null,
      "explanation": "",
      "raw_output": ""
    },
    {
      "model_name": "endorlabs_malicious_classifier",
      "sample_id": "npm_vant",
      "ground_truth": 1,
      "prediction": 1,
      "confidence": 0.9936923980712891,
      "inference_time_seconds": 0.2064378261566162,
      "cost_usd": null,
      "success": true,
      "error_message": null,
      "explanation": "",
      "raw_output": ""
    },
    {
      "model_name": "endorlabs_malicious_classifier",
      "sample_id": "npm_vite",
      "ground_truth": 0,
      "prediction": 1,
      "confidence": 0.9927341938018799,
      "inference_time_seconds": 0.22472119331359863,
      "cost_usd": null,
      "success": true,
      "error_message": null,
      "explanation": "",
      "raw_output": ""
    },
    {
      "model_name": "endorlabs_malicious_classifier",
      "sample_id": "npm_etag",
      "ground_truth": 0,
      "prediction": 1,
      "confidence": 0.9901818633079529,
      "inference_time_seconds": 0.24330997467041016,
      "cost_usd": null,
      "success": true,
      "error_message": null,
      "explanation": "",
      "raw_output": ""
    },
    {
      "model_name": "endorlabs_malicious_classifier",
      "sample_id": "pypi_inpout",
      "ground_truth": 0,
      "prediction": 1,
      "confidence": 0.9914127588272095,
      "inference_time_seconds": 0.24416184425354004,
      "cost_usd": null,
      "success": true,
      "error_message": null,
      "explanation": "",
      "raw_output": ""
    },
    {
      "model_name": "endorlabs_malicious_classifier",
      "sample_id": "npm_000webhost-cloud",
      "ground_truth": 1,
      "prediction": 1,
      "confidence": 0.9914773106575012,
      "inference_time_seconds": 0.23974609375,
      "cost_usd": null,
      "success": true,
      "error_message": null,
      "explanation": "",
      "raw_output": ""
    },
    {
      "model_name": "endorlabs_malicious_classifier",
      "sample_id": "npm_is-generator-function",
      "ground_truth": 0,
      "prediction": 1,
      "confidence": 0.9895456433296204,
      "inference_time_seconds": 0.20557522773742676,
      "cost_usd": null,
      "success": true,
      "error_message": null,
      "explanation": "",
      "raw_output": ""
    },
    {
      "model_name": "endorlabs_malicious_classifier",
      "sample_id": "npm_validator",
      "ground_truth": 0,
      "prediction": 1,
      "confidence": 0.9943122863769531,
      "inference_time_seconds": 0.2297039031982422,
      "cost_usd": null,
      "success": true,
      "error_message": null,
      "explanation": "",
      "raw_output": ""
    },
    {
      "model_name": "endorlabs_malicious_classifier",
      "sample_id": "npm_vant",
      "ground_truth": 1,
      "prediction": 1,
      "confidence": 0.9939686059951782,
      "inference_time_seconds": 0.2302079200744629,
      "cost_usd": null,
      "success": true,
      "error_message": null,
      "explanation": "",
      "raw_output": ""
    },
    {
      "model_name": "endorlabs_malicious_classifier",
      "sample_id": "npm_send",
      "ground_truth": 0,
      "prediction": 1,
      "confidence": 0.9912903308868408,
      "inference_time_seconds": 0.25028324127197266,
      "cost_usd": null,
      "success": true,
      "error_message": null,
      "explanation": "",
      "raw_output": ""
    },
    {
      "model_name": "endorlabs_malicious_classifier",
      "sample_id": "npm_finalhandler",
      "ground_truth": 0,
      "prediction": 1,
      "confidence": 0.9914650321006775,
      "inference_time_seconds": 0.3286600112915039,
      "cost_usd": null,
      "success": true,
      "error_message": null,
      "explanation": "",
      "raw_output": ""
    },
    {
      "model_name": "endorlabs_malicious_classifier",
      "sample_id": "npm_command-line-tool",
      "ground_truth": 0,
      "prediction": 1,
      "confidence": 0.9917928576469421,
      "inference_time_seconds": 0.22097110748291016,
      "cost_usd": null,
      "success": true,
      "error_message": null,
      "explanation": "",
      "raw_output": ""
    }
  ],
  "metrics": {
    "endorlabs_malicious_classifier": {
      "endorlabs_malicious_classifier_roc_auc": 0.6535947712418301,
      "endorlabs_malicious_classifier_pr_auc": 0.48616227635835474,
      "endorlabs_malicious_classifier_accuracy": 0.34615384615384615,
      "endorlabs_malicious_classifier_precision": 0.34615384615384615,
      "endorlabs_malicious_classifier_recall": 1.0,
      "endorlabs_malicious_classifier_f1": 0.5142857142857142,
      "endorlabs_malicious_classifier_true_positives": 9,
      "endorlabs_malicious_classifier_false_positives": 17,
      "endorlabs_malicious_classifier_true_negatives": 0,
      "endorlabs_malicious_classifier_false_negatives": 0,
      "endorlabs_malicious_classifier_sensitivity": 1.0,
      "endorlabs_malicious_classifier_specificity": 0.0,
      "endorlabs_malicious_classifier_positive_predictive_value": 0.34615384615384615,
      "endorlabs_malicious_classifier_fpr_at_95tpr": 0.7647058823529411,
      "endorlabs_malicious_classifier_fpr_at_90tpr": 0.7647058823529411,
      "endorlabs_malicious_classifier_num_samples": 26,
      "endorlabs_malicious_classifier_num_positive": 9,
      "endorlabs_malicious_classifier_num_negative": 17,
      "endorlabs_malicious_classifier_class_balance": 0.34615384615384615,
      "endorlabs_malicious_classifier_score_mean": 0.9920282753614279,
      "endorlabs_malicious_classifier_score_std": 0.0013718726875557997,
      "endorlabs_malicious_classifier_score_min": 0.9894092082977295,
      "endorlabs_malicious_classifier_score_max": 0.9943122863769531,
      "endorlabs_malicious_classifier_avg_inference_time": 0.23226764568915734,
      "endorlabs_malicious_classifier_total_cost_usd": 0,
      "endorlabs_malicious_classifier_success_rate": 1.0
    }
  }
}